Jinja2ZhongwenWendang/README.md
Jinja2ZhongwenWendang/__init__.py
Jinja2ZhongwenWendang/__main__.py
Jinja2ZhongwenWendang/file.epub
Jinja2ZhongwenWendang/index.html
Jinja2ZhongwenWendang/css/__init__.py
Jinja2ZhongwenWendang/css/annotations.css
Jinja2ZhongwenWendang/css/main.css
Jinja2ZhongwenWendang/css/normalize.css
Jinja2ZhongwenWendang/css/popup.css
Jinja2ZhongwenWendang/font/__init__.py
Jinja2ZhongwenWendang/font/fontello.eot
Jinja2ZhongwenWendang/font/fontello.svg
Jinja2ZhongwenWendang/font/fontello.ttf
Jinja2ZhongwenWendang/font/fontello.woff
Jinja2ZhongwenWendang/img/__init__.py
Jinja2ZhongwenWendang/img/annotator-glyph-sprite.png
Jinja2ZhongwenWendang/img/annotator-icon-sprite.png
Jinja2ZhongwenWendang/img/apple-touch-icon.png
Jinja2ZhongwenWendang/img/cancelfullscreen.png
Jinja2ZhongwenWendang/img/close.png
Jinja2ZhongwenWendang/img/fullscreen.png
Jinja2ZhongwenWendang/img/loader.gif
Jinja2ZhongwenWendang/img/menu-icon.png
Jinja2ZhongwenWendang/img/save.png
Jinja2ZhongwenWendang/img/saved.png
Jinja2ZhongwenWendang/img/settings-s.png
Jinja2ZhongwenWendang/img/settings.png
Jinja2ZhongwenWendang/img/star.png
Jinja2ZhongwenWendang/js/__init__.py
Jinja2ZhongwenWendang/js/epub.js
Jinja2ZhongwenWendang/js/epub.min.js
Jinja2ZhongwenWendang/js/epub.min.map
Jinja2ZhongwenWendang/js/hooks.min.js
Jinja2ZhongwenWendang/js/hooks.min.map
Jinja2ZhongwenWendang/js/reader.js
Jinja2ZhongwenWendang/js/reader.js.map
Jinja2ZhongwenWendang/js/reader.min.js
Jinja2ZhongwenWendang/js/reader.min.map
Jinja2ZhongwenWendang/js/hooks/__init__.py
Jinja2ZhongwenWendang/js/hooks/extensions/__init__.py
Jinja2ZhongwenWendang/js/hooks/extensions/highlight.js
Jinja2ZhongwenWendang/js/libs/__init__.py
Jinja2ZhongwenWendang/js/libs/jquery.min.js
Jinja2ZhongwenWendang/js/libs/localforage.min.js
Jinja2ZhongwenWendang/js/libs/screenfull.js
Jinja2ZhongwenWendang/js/libs/screenfull.min.js
Jinja2ZhongwenWendang/js/libs/zip.min.js
Jinja2ZhongwenWendang/js/plugins/__init__.py
jinja2_zhongwen_wendang-2024.3.1.0.dist-info/METADATA
jinja2_zhongwen_wendang-2024.3.1.0.dist-info/WHEEL
jinja2_zhongwen_wendang-2024.3.1.0.dist-info/entry_points.txt
jinja2_zhongwen_wendang-2024.3.1.0.dist-info/top_level.txt
jinja2_zhongwen_wendang-2024.3.1.0.dist-info/RECORD
